converter/__init__.py
converter/cli.py
converter/core/__init__.py
converter/core/converter.py
converter/core/doc_converter.py
converter/core/image_converter.py
converter/core/md_converter.py
converter/core/pdf_converter.py
converter/core/template_manager.py
converter/templates/__init__.py
converter/templates/template_manager.py
converter/templates/academic/config.json
converter/templates/academic/script.js
converter/templates/academic/style.css
converter/templates/academic/template.html
converter/templates/article/config.json
converter/templates/article/script.js
converter/templates/article/style.css
converter/templates/article/template.html
converter/templates/blog/blog.css
converter/templates/blog/blog.js
converter/templates/blog/config.json
converter/templates/blog/preview.png
converter/templates/blog/script.js
converter/templates/blog/style.css
converter/templates/blog/template.html
converter/templates/blog/template.json
converter/templates/default/config.json
converter/templates/default/preview.png
converter/templates/default/style.css
converter/templates/default/template.html
converter/templates/default/template.json
converter/templates/ebook/config.json
converter/templates/ebook/style.css
converter/templates/ebook/template.html
converter/templates/magazine/config.json
converter/templates/magazine/script.js
converter/templates/magazine/style.css
converter/templates/magazine/template.html
converter/templates/minimal/config.json
converter/templates/minimal/style.css
converter/templates/minimal/template.html
converter/templates/modern/config.json
converter/templates/modern/style.css
converter/templates/modern/template.html
converter/templates/official/config.json
converter/templates/official/style.css
converter/templates/official/template.html
converter/templates/technical/config.json
converter/templates/technical/style.css
converter/templates/technical/template.html
converter/templates/webpage/config.json
converter/templates/webpage/style.css
tl_markdown_converter-1.0.3.dist-info/METADATA
tl_markdown_converter-1.0.3.dist-info/PKG-INFO 2
tl_markdown_converter-1.0.3.dist-info/SOURCES 2.txt
tl_markdown_converter-1.0.3.dist-info/WHEEL
tl_markdown_converter-1.0.3.dist-info/dependency_links 2.txt
tl_markdown_converter-1.0.3.dist-info/entry_points 2.txt
tl_markdown_converter-1.0.3.dist-info/entry_points.txt
tl_markdown_converter-1.0.3.dist-info/requires 2.txt
tl_markdown_converter-1.0.3.dist-info/top_level 2.txt
tl_markdown_converter-1.0.3.dist-info/top_level.txt
tl_markdown_converter-1.0.3.dist-info/RECORD
