Metadata-Version: 2.2
Name: tl-markdown-converter
Version: 1.0.3
Summary: A powerful and flexible Markdown converter supporting multiple output formats and templates
Home-page: https://github.com/fiction/markdown-converter
Author: TL
Author-email: ttieli@gmail.com
Classifier: Development Status :: 4 - Beta
Classifier: Intended Audience :: Developers
Classifier: Topic :: Software Development :: Libraries :: Python Modules
Classifier: Topic :: Text Processing :: Markup :: Markdown
Classifier: License :: OSI Approved :: MIT License
Classifier: Programming Language :: Python :: 3
Classifier: Programming Language :: Python :: 3.8
Classifier: Programming Language :: Python :: 3.9
Classifier: Programming Language :: Python :: 3.10
Classifier: Programming Language :: Python :: 3.11
Requires-Python: >=3.8
Requires-Dist: markdown>=3.3.0
Requires-Dist: jinja2>=3.0.0
Requires-Dist: Pillow>=9.0.0
Requires-Dist: beautifulsoup4>=4.9.0
Requires-Dist: playwright>=1.20.0
Requires-Dist: python-docx>=0.8.11
Requires-Dist: weasyprint>=54.0
Requires-Dist: argparse>=1.4.0
Requires-Dist: python-dotenv>=0.19.0
Requires-Dist: rich>=10.0.0
Dynamic: author
Dynamic: author-email
Dynamic: classifier
Dynamic: description
Dynamic: description-content-type
Dynamic: home-page
Dynamic: requires-dist
Dynamic: requires-python
Dynamic: summary
